{"chunk_definitions":[{"row":515,"row_count":1,"visible":true,"expansion_state":0,"options":{"engine":"r","label":"load_data_from_PD","eval":"readPD_files","echo":false,"message":false,"warning":false,"results":"asis"},"document_id":"78E1C5D0","chunk_id":"c74q92nvsnbzd","chunk_label":"load_data_from_PD"},{"row":598,"row_count":1,"visible":true,"expansion_state":0,"options":{"engine":"r","label":"load_data_from_MQ","eval":"readMQ_files","echo":false,"message":false,"warning":false,"results":"asis"},"document_id":"D088F704","chunk_id":"c7ta1ats0m730","chunk_label":"load_data_from_MQ"}],"doc_write_time":1669113812}